{
  "date": "2026-05-07",
  "generated_at": "2026-05-07T20:24:02",
  "metrics": {
    "total": 38,
    "open_count": 34,
    "delivered_count": 0,
    "escalated_count": 3,
    "escalated_pct": "8%",
    "review_avg": "3.7",
    "review_median": "4",
    "review_min": "1",
    "review_max": "10",
    "review_substantive_count": 33,
    "upstream_avg": "32.8",
    "upstream_median": "28",
    "priority_set_count": 33,
    "priority_unset_count": 5,
    "ba_avg": "2.2",
    "ba_count": 6,
    "ba_pending_total": "6 of 38",
    "total_passed_to_it": 17,
    "sprint_passed_count": 15,
    "admin_request_count": 2,
    "passed_to_it_rate": "45%",
    "ba_to_it_cycle_avg": "1",
    "ba_to_it_dated_count": 1,
    "yield_substantive": 33,
    "yield_substantive_pct": "87%",
    "yield_gate": 4,
    "yield_gate_pct": "11%",
    "yield_pending": 1,
    "yield_pending_pct": "3%",
    "yield_pending_names": "USCIS Interview Phase 2 Record",
    "flow_weeks": {
      "16": 23,
      "17": 4,
      "18": 5,
      "19": 6
    },
    "flow_week_labels": [
      16,
      17,
      18,
      19
    ],
    "flow_bar_pcts": [
      "100%",
      "17%",
      "22%",
      "26%"
    ],
    "flow_max": 23,
    "donut_total_open": 34,
    "donut_segments": [
      {
        "name": "Triage",
        "count": 16,
        "pct": 47.1,
        "dasharray": 47.1,
        "dashoffset": 25.0,
        "stroke_css": "var(--indigo)",
        "gradient_id": "donut-grad-0",
        "hex_start": "#5e5ce6",
        "hex_end": "#bf5af2"
      },
      {
        "name": "IT Prioritization",
        "count": 8,
        "pct": 23.5,
        "dasharray": 23.5,
        "dashoffset": -22.1,
        "stroke_css": "var(--orange)",
        "gradient_id": "donut-grad-1",
        "hex_start": "#ff9f0a",
        "hex_end": "#ff375f"
      },
      {
        "name": "UAT/Testing",
        "count": 7,
        "pct": 20.6,
        "dasharray": 20.6,
        "dashoffset": -45.6,
        "stroke_css": "var(--green)",
        "gradient_id": "donut-grad-2",
        "hex_start": "#30d158",
        "hex_end": "#30d158"
      },
      {
        "name": "In Progress",
        "count": 1,
        "pct": 2.9,
        "dasharray": 2.9,
        "dashoffset": -66.2,
        "stroke_css": "var(--cyan)",
        "gradient_id": "donut-grad-3",
        "hex_start": "#64d2ff",
        "hex_end": "#0a84ff"
      },
      {
        "name": "Rejected",
        "count": 1,
        "pct": 2.9,
        "dasharray": 2.9,
        "dashoffset": -69.1,
        "stroke_css": "var(--purple)",
        "gradient_id": "donut-grad-4",
        "hex_start": "#bf5af2",
        "hex_end": "#5e5ce6"
      },
      {
        "name": "New Request",
        "count": 1,
        "pct": 2.9,
        "dasharray": 2.9,
        "dashoffset": -72.0,
        "stroke_css": "var(--yellow)",
        "gradient_id": "donut-grad-5",
        "hex_start": "#ffd60a",
        "hex_end": "#ff9f0a"
      }
    ],
    "work_type_counts": {
      "Task Set changes": 11,
      "Automation changes": 6,
      "Picklist changes": 6,
      "New / Modified Fields": 5,
      "Template changes": 2,
      "Stage changes": 2,
      "Object modifications": 1,
      "No action / Already done": 4,
      "TBD": 0
    },
    "work_type_max": 11,
    "dept_counts": {
      "Business Development": 6,
      "Phase 2": 27,
      "CSC": 3,
      "Inventory Control": 1,
      "Phase 1": 1
    },
    "dept_cards": [
      {
        "name": "Phase 2",
        "count": 27,
        "pct": "71.1%",
        "bar_width": "100%",
        "css_color": "var(--indigo)",
        "hex": "#5e5ce6"
      },
      {
        "name": "Business Development",
        "count": 6,
        "pct": "15.8%",
        "bar_width": "22%",
        "css_color": "var(--orange)",
        "hex": "#ff9f0a"
      },
      {
        "name": "CSC",
        "count": 3,
        "pct": "7.9%",
        "bar_width": "11%",
        "css_color": "var(--mint)",
        "hex": "#63e6e2"
      },
      {
        "name": "Inventory Control",
        "count": 1,
        "pct": "2.6%",
        "bar_width": "4%",
        "css_color": "var(--yellow)",
        "hex": "#ffd60a"
      },
      {
        "name": "Phase 1",
        "count": 1,
        "pct": "2.6%",
        "bar_width": "4%",
        "css_color": "var(--green)",
        "hex": "#30d158"
      }
    ],
    "top_dept_name": "Phase 2",
    "pm_counts": {
      "Maria Garcia": 20,
      "Jessie Logan": 1,
      "David Molano": 18
    },
    "team_mar_count": 20,
    "team_mar_pct": "53%",
    "team_david_count": 18,
    "team_david_pct": "47%",
    "rec_workload_note": "20/18 \u2014 Mar is +11% this week",
    "tw_intakes": 6,
    "tw_reviews": 8,
    "tw_avg_cycle": "3.8",
    "tw_gate": 0,
    "tw_escalated": 0,
    "lw_intakes": 5,
    "lw_reviews": 6,
    "lw_avg_cycle": "2.8",
    "lw_gate": 1,
    "lw_escalated": 0,
    "lw_has_reviews": true,
    "tm_intakes": 6,
    "tm_reviewed": 8,
    "tm_avg_cycle": "3.8",
    "tm_escalated": 0,
    "tm_gate": 0,
    "lm_intakes": 32,
    "lm_reviews": 29,
    "lm_avg_cycle": "3.6",
    "lm_escalated": 3,
    "lm_has_coe": true,
    "six_mo_intakes": 38,
    "six_mo_reviews": 37,
    "six_mo_avg_cycle": "3.7",
    "days_coe_active": 22,
    "pre_coe_days": 174,
    "w_current": 19,
    "w_minus1": 18,
    "w_minus2": 17,
    "w_minus3": 16,
    "rec_it_prio_count": 8,
    "rec_status_color_blank": "30 of 38",
    "rec_no_color_count": 30,
    "rec_ba_count": 6,
    "tw_window_label": "May 4 \u2013 Today",
    "lw_window_label": "Apr 27 \u2013 May 3",
    "tm_month_name": "May",
    "tm_window_label": "May 1 \u2013 May 31",
    "lm_month_name": "April",
    "lm_window_label": "Apr 1 \u2013 Apr 30",
    "six_mo_window_label": "Nov 2025 \u2013 May 2026",
    "top_work_type": "Task Set changes",
    "flow_peak_week_label": "W16",
    "flow_peak_count": 23,
    "flow_w_minus3_range": "Apr 13 \u2013 Apr 19",
    "flow_w_minus2_range": "Apr 20 \u2013 Apr 26",
    "flow_w_minus1_range": "Apr 27 \u2013 May 3",
    "flow_w_current_range": "May 4 \u2013 Now",
    "pending_received_label": "May 6",
    "coe_start_display": "April 15, 2026",
    "coe_start_date": "2026-04-15",
    "stage_current": {
      "New Request": 1,
      "Triage": 16,
      "IT Prioritization": 8,
      "In Progress": 1,
      "UAT/Testing": 7,
      "Awaiting Next Sprint": 0,
      "On Hold": 0
    },
    "stage_cards": [
      {
        "name": "New Request",
        "count": 1,
        "delta": -4,
        "baseline_label": "from last week",
        "empty_note": null,
        "color": "#4f7ef0",
        "slug": "new_request",
        "sparkline": [
          0,
          0,
          0,
          0,
          0,
          0,
          3,
          1
        ]
      },
      {
        "name": "Triage",
        "count": 16,
        "delta": 7,
        "baseline_label": "from last week",
        "empty_note": null,
        "color": "#a463f5",
        "slug": "triage",
        "sparkline": [
          0,
          0,
          0,
          0,
          0,
          0,
          8,
          16
        ]
      },
      {
        "name": "IT Prioritization",
        "count": 8,
        "delta": 6,
        "baseline_label": "from last week",
        "empty_note": null,
        "color": "#e1417a",
        "slug": "it_prioritization",
        "sparkline": [
          0,
          0,
          0,
          0,
          0,
          0,
          8,
          8
        ]
      },
      {
        "name": "In Progress",
        "count": 1,
        "delta": -7,
        "baseline_label": "from last week",
        "empty_note": null,
        "color": "#e87a3a",
        "slug": "in_progress",
        "sparkline": [
          0,
          0,
          0,
          0,
          0,
          0,
          8,
          1
        ]
      },
      {
        "name": "UAT/Testing",
        "count": 7,
        "delta": 7,
        "baseline_label": "from last week",
        "empty_note": null,
        "color": "#30d158",
        "slug": "uat_testing",
        "sparkline": [
          0,
          0,
          0,
          0,
          0,
          0,
          0,
          7
        ]
      },
      {
        "name": "Awaiting Next Sprint",
        "count": 0,
        "delta": -3,
        "baseline_label": "from last week",
        "empty_note": "all moved to next stage",
        "color": "#d4a23a",
        "slug": "awaiting_next_sprint",
        "sparkline": [
          0,
          0,
          0,
          0,
          0,
          0,
          0,
          0
        ]
      },
      {
        "name": "On Hold",
        "count": 0,
        "delta": 0,
        "baseline_label": "from last week",
        "empty_note": null,
        "color": "#8e8e93",
        "slug": "on_hold",
        "sparkline": [
          0,
          0,
          0,
          0,
          0,
          0,
          0,
          0
        ]
      }
    ],
    "backlog_total": 33,
    "backlog_prior": 27,
    "backlog_delta": 6,
    "backlog_intakes_this_week": 6,
    "backlog_completed_this_week": 0,
    "backlog_closed_this_week": 0,
    "intakes_last_week": 5,
    "completed_last_week": 0,
    "closed_last_week": 1,
    "has_history": true,
    "outcome_closed_at_review": 0,
    "outcome_rejected": 4,
    "outcome_pushed_to_epmo": 0,
    "outcome_on_hold": 3,
    "outcome_delivered": 0,
    "outcome_admin_request": 2,
    "area_chart": {
      "labels": [
        "W12",
        "W13",
        "W14",
        "W15",
        "W16",
        "W17",
        "W18",
        "W19"
      ],
      "stages": [
        {
          "name": "New Request",
          "color": "#4f7ef0",
          "values": [
            0,
            0,
            0,
            0,
            0,
            0,
            3,
            1
          ]
        },
        {
          "name": "Triage",
          "color": "#a463f5",
          "values": [
            0,
            0,
            0,
            0,
            0,
            0,
            8,
            16
          ]
        },
        {
          "name": "IT Prioritization",
          "color": "#e1417a",
          "values": [
            0,
            0,
            0,
            0,
            0,
            0,
            8,
            8
          ]
        },
        {
          "name": "In Progress",
          "color": "#e87a3a",
          "values": [
            0,
            0,
            0,
            0,
            0,
            0,
            8,
            1
          ]
        },
        {
          "name": "UAT/Testing",
          "color": "#30d158",
          "values": [
            0,
            0,
            0,
            0,
            0,
            0,
            0,
            7
          ]
        },
        {
          "name": "Awaiting Next Sprint",
          "color": "#d4a23a",
          "values": [
            0,
            0,
            0,
            0,
            0,
            0,
            0,
            0
          ]
        },
        {
          "name": "On Hold",
          "color": "#8e8e93",
          "values": [
            0,
            0,
            0,
            0,
            0,
            0,
            0,
            0
          ]
        }
      ],
      "polygons": [
        "40.0,244.0 134.3,244.0 228.6,244.0 322.9,244.0 417.1,244.0 511.4,244.0 605.7,224.5 700.0,237.5 700.0,244.0 605.7,244.0 511.4,244.0 417.1,244.0 322.9,244.0 228.6,244.0 134.3,244.0 40.0,244.0",
        "40.0,244.0 134.3,244.0 228.6,244.0 322.9,244.0 417.1,244.0 511.4,244.0 605.7,172.3 700.0,133.3 700.0,237.5 605.7,224.5 511.4,244.0 417.1,244.0 322.9,244.0 228.6,244.0 134.3,244.0 40.0,244.0",
        "40.0,244.0 134.3,244.0 228.6,244.0 322.9,244.0 417.1,244.0 511.4,244.0 605.7,120.2 700.0,81.1 700.0,133.3 605.7,172.3 511.4,244.0 417.1,244.0 322.9,244.0 228.6,244.0 134.3,244.0 40.0,244.0",
        "40.0,244.0 134.3,244.0 228.6,244.0 322.9,244.0 417.1,244.0 511.4,244.0 605.7,68.1 700.0,74.6 700.0,81.1 605.7,120.2 511.4,244.0 417.1,244.0 322.9,244.0 228.6,244.0 134.3,244.0 40.0,244.0",
        "40.0,244.0 134.3,244.0 228.6,244.0 322.9,244.0 417.1,244.0 511.4,244.0 605.7,68.1 700.0,29.0 700.0,74.6 605.7,68.1 511.4,244.0 417.1,244.0 322.9,244.0 228.6,244.0 134.3,244.0 40.0,244.0",
        "40.0,244.0 134.3,244.0 228.6,244.0 322.9,244.0 417.1,244.0 511.4,244.0 605.7,68.1 700.0,29.0 700.0,29.0 605.7,68.1 511.4,244.0 417.1,244.0 322.9,244.0 228.6,244.0 134.3,244.0 40.0,244.0",
        "40.0,244.0 134.3,244.0 228.6,244.0 322.9,244.0 417.1,244.0 511.4,244.0 605.7,68.1 700.0,29.0 700.0,29.0 605.7,68.1 511.4,244.0 417.1,244.0 322.9,244.0 228.6,244.0 134.3,244.0 40.0,244.0"
      ],
      "y_max": 35,
      "x_labels": [
        {
          "x": 40.0,
          "label": "W12"
        },
        {
          "x": 134.28571428571428,
          "label": "W13"
        },
        {
          "x": 228.57142857142858,
          "label": "W14"
        },
        {
          "x": 322.85714285714283,
          "label": "W15"
        },
        {
          "x": 417.14285714285717,
          "label": "W16"
        },
        {
          "x": 511.42857142857144,
          "label": "W17"
        },
        {
          "x": 605.7142857142857,
          "label": "W18"
        },
        {
          "x": 700.0,
          "label": "W19"
        }
      ],
      "y_labels": [
        {
          "y": 244.0,
          "label": "0"
        },
        {
          "y": 133.25714285714287,
          "label": "17"
        },
        {
          "y": 16.0,
          "label": "35"
        }
      ],
      "width": 720,
      "height": 280,
      "pad_left": 40,
      "pad_top": 16,
      "plot_w": 660,
      "plot_h": 228,
      "has_data": true,
      "weeks_with_data": 2
    },
    "aging_by_stage": {
      "New Request": {
        "count": 1,
        "oldest": 1,
        "avg": 1.0,
        "stuck": 0
      },
      "Triage": {
        "count": 16,
        "oldest": 17,
        "avg": 7.6,
        "stuck": 6
      },
      "IT Prioritization": {
        "count": 9,
        "oldest": 8,
        "avg": 6.0,
        "stuck": 0
      },
      "In Progress": {
        "count": 1,
        "oldest": 10,
        "avg": 10.0,
        "stuck": 0
      },
      "UAT/Testing": {
        "count": 7,
        "oldest": 3,
        "avg": 1.1,
        "stuck": 0
      },
      "Awaiting Next Sprint": {
        "count": 0,
        "oldest": 0,
        "avg": 0,
        "stuck": 0
      },
      "On Hold": {
        "count": 0,
        "oldest": 0,
        "avg": 0,
        "stuck": 0
      }
    },
    "throughput_biweekly": [
      {
        "period_start": "2026-03-23",
        "label": "W13\u2013W14",
        "count": 0
      },
      {
        "period_start": "2026-04-06",
        "label": "W15\u2013W16",
        "count": 1
      },
      {
        "period_start": "2026-04-20",
        "label": "W17\u2013W18",
        "count": 5
      },
      {
        "period_start": "2026-05-04",
        "label": "W19\u2013W20",
        "count": 0
      }
    ],
    "throughput_avg": 1.5,
    "intake_avg_biweekly": 9.5,
    "pace": {
      "state": "off_pace",
      "label": "Off pace",
      "ratio": 0.16,
      "net_per_period": 8.0,
      "net_per_month": 17.4,
      "intake_avg": 9.5,
      "throughput_avg": 1.5
    },
    "oldest_open_days": 17,
    "oldest_open_stage": "Triage",
    "stuck_total": 6,
    "it_cycle": {
      "build": {
        "avg": 7.3,
        "median": 8,
        "count": 7,
        "min": 5,
        "max": 8
      },
      "testing": {
        "avg": null,
        "median": null,
        "count": 0,
        "min": 0,
        "max": 0
      },
      "closeout": {
        "avg": null,
        "median": null,
        "count": 0,
        "min": 0,
        "max": 0
      },
      "total": {
        "avg": null,
        "median": null,
        "count": 0,
        "min": 0,
        "max": 0
      }
    }
  }
}